setup.py
distributions/Binomialdistribution.py
distributions/Gaussiandistribution.py
distributions/Generaldistribution.py
distributions/__init__.py
distributions_ramtin_movahed.egg-info/PKG-INFO
distributions_ramtin_movahed.egg-info/SOURCES.txt
distributions_ramtin_movahed.egg-info/dependency_links.txt
distributions_ramtin_movahed.egg-info/not-zip-safe
distributions_ramtin_movahed.egg-info/top_level.txt